LICENSE
MANIFEST.in
README.rst
setup.py
tibas/__init__.py
tibas.tt.egg-info/PKG-INFO
tibas.tt.egg-info/SOURCES.txt
tibas.tt.egg-info/dependency_links.txt
tibas.tt.egg-info/namespace_packages.txt
tibas.tt.egg-info/requires.txt
tibas.tt.egg-info/top_level.txt
tibas/tt/__init__.py
tibas/tt/layout.html
tibas/tt/theme.conf
tibas/tt/static/tt.css
tibas/tt/static/fonts/concrete/OFL-FAQ.txt
tibas/tt/static/fonts/concrete/OFL.txt
tibas/tt/static/fonts/concrete/README.txt
tibas/tt/static/fonts/concrete/cmun-concrete.css
tibas/tt/static/fonts/concrete/cmunobi.eot
tibas/tt/static/fonts/concrete/cmunobi.svg
tibas/tt/static/fonts/concrete/cmunobi.ttf
tibas/tt/static/fonts/concrete/cmunobi.woff
tibas/tt/static/fonts/concrete/cmunobx.eot
tibas/tt/static/fonts/concrete/cmunobx.svg
tibas/tt/static/fonts/concrete/cmunobx.ttf
tibas/tt/static/fonts/concrete/cmunobx.woff
tibas/tt/static/fonts/concrete/cmunorm.eot
tibas/tt/static/fonts/concrete/cmunorm.svg
tibas/tt/static/fonts/concrete/cmunorm.ttf
tibas/tt/static/fonts/concrete/cmunorm.woff
tibas/tt/static/fonts/concrete/cmunoti.eot
tibas/tt/static/fonts/concrete/cmunoti.svg
tibas/tt/static/fonts/concrete/cmunoti.ttf
tibas/tt/static/fonts/concrete/cmunoti.woff
tibas/tt/static/fonts/istok/istok.woff
tibas/tt/static/fonts/typewriter/OFL-FAQ.txt
tibas/tt/static/fonts/typewriter/OFL.txt
tibas/tt/static/fonts/typewriter/README.txt
tibas/tt/static/fonts/typewriter/cmun-typewriter.css
tibas/tt/static/fonts/typewriter/cmunit.eot
tibas/tt/static/fonts/typewriter/cmunit.svg
tibas/tt/static/fonts/typewriter/cmunit.ttf
tibas/tt/static/fonts/typewriter/cmunit.woff
tibas/tt/static/fonts/typewriter/cmuntb.eot
tibas/tt/static/fonts/typewriter/cmuntb.svg
tibas/tt/static/fonts/typewriter/cmuntb.ttf
tibas/tt/static/fonts/typewriter/cmuntb.woff
tibas/tt/static/fonts/typewriter/cmuntt.eot
tibas/tt/static/fonts/typewriter/cmuntt.svg
tibas/tt/static/fonts/typewriter/cmuntt.ttf
tibas/tt/static/fonts/typewriter/cmuntt.woff
tibas/tt/static/fonts/typewriter/cmuntx.eot
tibas/tt/static/fonts/typewriter/cmuntx.svg
tibas/tt/static/fonts/typewriter/cmuntx.ttf
tibas/tt/static/fonts/typewriter/cmuntx.woff