Metadata-Version: 1.0
Name: tibas.tt
Version: 0.3.1
Summary: A Sphinx/ablog theme that inherits and works off alabaster
Home-page: http://bitbucket.org/gabriel.montagne/tibas.tt
Author: gabriel montangé láscaris-comneno
Author-email: gabriel@tibas.london
License: MIT
Platform: any
